[{"sales": 207, "product": "Mouse", "city": "South Babyboro", "id": "d61d98bb-ee3b-439a-ad9f-a05d1f9e9a91"},
{"city": "New Faye", "product": "Pizza", "sales": 508, "id": "d235fca7-1fd7-48f2-"},
{"product": "Towels", "city": "Rennershire", "sales": 191, "id": "c973867f-3328-4af"},
{"sales": 324, "city": "Gastonia", "product": "Gloves", "id": "73fd676f-3db9-4bae-9e54-6254"},
{"city": "Port Talonhaven", "product": "Keyboard", "sales": 964, "id": "9e4f84fa-5652-4122-b"},
{"sales": 826, "product": "Sausages", "city": "San Marcos", "id": "fe6d2291-bb84-4d2d-b3eb-b6"},
{"city": "Port Rita", "product": "Keyboard", "sales": 740, "id": "f4d7f30f-4654-4f52-bc37-1b146c2"},
{"city": "Lake Prudence", "product": "Bike", "sales": 526, "id": "b30230e1-0abc-4895-b39"},
{"sales": 176, "product": "Chair", "city": "Schadentown", "id": "57d87525-7ac2-4"},
{"product": "Sausages", "sales": 703, "city": "Morissettecester", "id": "e825cd29-df5e-4728-acba-23abf8e"},
{"city": "Kuhicfurt", "product": "Shoes", "sales": 868, "id": "ea07f014-"},
{"city": "Edwinchester", "product": "Pants", "sales": 673, "id": "2ca24c06"},
{"city": "Fort Destiney", "product": "Computer", "sales": 981, "id": "29"},
{"product": "Bacon", "city": "West Ernesto", "sales": 136, "id": "08b933a0-d456-4c36-830d-579b9cce"},
{"city": "South Vanessafield", "product": "Shirt", "sales": 924, "id": "4998820e-a486-47c1-a469-"},
{"city": "Springfield", "sales": 626, "product": "Keyboard", "id": "8fa2f63c-"},
{"city": "North Okeyview", "product": "Computer", "sales": 369, "id": "81946123-e73d-4f13-941b-d"},
{"sales": 169, "product": "Sausages", "city": "Ivyfort", "id": "11ff2779-1e6e-4bc2-b3aa-5a24"},
{"city": "New Pete", "product": "Gloves", "sales": 965, "id": "03dcb893-0a82-4208"},
{"sales": 316, "product": "Chips", "city": "Bethelville", "id": "2ca5"},
{"city": "Paulbury", "product": "Fish", "sales": 390, "id": "98c68f81-ae9c"},
{"city": "West Murieltown", "sales": 914, "product": "Car", "id": "66d68866-43e7-4854-bafa-67a4e54a"},
{"sales": 931, "product": "Towels", "city": "Greeley", "id": "1f72479c-d238-4aef-8024-270ab"},
{"sales": 462, "product": "Bacon", "city": "South Lexus", "id": "b2331a54-34b9-4482-94e7-3db668a4c459"},
{"sales": 182, "city": "Destinyboro", "product": "Sausages", "id": "5ded83d2-8ae7-"},
{"city": "Rosaliaboro", "sales": 994, "product": "Table", "id": "9002efab-944a-4b6f-b3e7-da08c759ceeb"},
{"city": "South Maurice", "sales": 700, "product": "Pizza", "id": "beb31000-ba36-49c6-957b-69ae26b8539"},
{"product": "Shirt", "city": "Lake Amir", "sales": 480, "id": "52843618-ae4f-48"},
{"product": "Cheese", "city": "Arnoldofurt", "sales": 265, "id": "1c2acff4-9066-4550-959c-3231634a6b"},
{"city": "Arlieview", "product": "Pants", "sales": 381, "id": "a7"},
{"city": "Fort Al", "product": "Tuna", "sales": 225, "id": "f4ad0f19-ff59-"},
{"city": "Veumport", "product": "Sausages", "sales": 557, "id": "584099a6-c654-491b-9d6"},
{"sales": 700, "product": "Towels", "city": "Bryan", "id": "1bab9bcb-ed63"},
{"sales": 549, "product": "Towels", "city": "South Joseborough", "id": "7d6d2f05-f9eb-4055-9064-3e61f4b4408e"},
{"city": "Rhetttown", "product": "Computer", "sales": 557, "id": "a972b886-3ec6-4c9d-9a29-69"},
{"city": "Bernhardview", "product": "Ball", "sales": 903, "id": "06124dbb-cdff-4936-a"},
{"product": "Soap", "sales": 996, "city": "Carson City", "id": "4a04cbff-5930-44a5-94c8-84dee163d930"},
{"product": "Pizza", "city": "South Adelialand", "sales": 729, "id": "15303da7-1ba5-428"},
{"city": "Vandervortchester", "product": "Chair", "sales": 580, "id": "0aa99055-2898-488c-b8ae-"},
{"city": "North Vancehaven", "sales": 168, "product": "Tuna", "id": "1651f766-e2b3-45ff"},
{"product": "Fish", "city": "East Rodolfostad", "sales": 120, "id": "20ad7d0c-b308-4"},
{"product": "Chips", "sales": 109, "city": "Davie", "id": "a5b"},
{"sales": 414, "product": "Chips", "city": "South Emmyborough", "id": "06e865c4-a"},
{"product": "Hat", "city": "South Tremayne", "sales": 240, "id": "67a77487-5cef-475"},
{"city": "East Ardithtown", "product": "Hat", "sales": 491, "id": "84e588b2-bde"},
{"city": "Fort Hanna", "product": "Computer", "sales": 547, "id": "30f78e28-c755-456d-aa93-2cdbf5cb"},
{"product": "Shirt", "sales": 630, "city": "Cleveland", "id": "4440ef29-5d72"},
{"product": "Soap", "city": "West Eliezer", "sales": 894, "id": "b9"},
{"city": "Emmerichland", "product": "Bacon", "sales": 396, "id": "05d7c326-5795-46e9-bc3d-9b4df8d"},
{"city": "Elenorboro", "product": "Shirt", "sales": 745, "id": "b0814816-acfe-4fb8-a8b8-2e6f11684b"},
{"sales": 370, "city": "Palmdale", "product": "Ball", "id": "9dfb37b9-c2c2-4240-b046-d09d64b604"},
{"sales": 148, "product": "Tuna", "city": "Josiemouth", "id": "16c940b3-813b-41"},
{"city": "North Dantecester", "product": "Chips", "sales": 445, "id": "db83976"},
{"city": "Greeley", "product": "Cheese", "sales": 614, "id": "a796f8c7-1909-49d6-bfd1-010483486d1b"},
{"sales": 753, "product": "Hat", "city": "Jeradland", "id": "3372d97f-309b-4b33-b"},
{"sales": 326, "product": "Soap", "city": "Gardena", "id": "e6cb41da-e548-4174-b9a2-aec90a7613"},
{"city": "Agustinafurt", "product": "Ball", "sales": 772, "id": "3db"},
{"city": "Clintonborough", "product": "Table", "sales": 691, "id": "efc23d7c-bf"},
{"sales": 616, "product": "Gloves", "city": "Oberbrunnerview", "id": "fa222513-63a4-4536-a5cd-4d136e4b0a"},
{"sales": 281, "city": "Remingtonchester", "product": "Keyboard", "id": "417322da-b124-4c79-8364-13475e1ee8bd"},
{"product": "Hat", "city": "Fosterworth", "sales": 775, "id": "d4968455-788f-4aa9-bcbd-f1"},
{"city": "Gottliebfield", "product": "Hat", "sales": 137, "id": "52d00de6-4495-4581-a387-955bce5b21cc"},
{"product": "Chicken", "sales": 243, "city": "Fort Carmeloshire", "id": "fff54"},
{"product": "Fish", "sales": 842, "city": "Port Abnercester", "id": "b420b0fa-a589-4a90-a514-4"},
{"sales": 220, "product": "Bacon", "city": "East Cierra", "id": "50e64f5f-a59b-421f-aed6-584ccb5dc9"},
{"city": "Lake Sigurd", "product": "Mouse", "sales": 215, "id": "6df6bf56-b496-4fec-8d02-"},
{"sales": 442, "product": "Computer", "city": "Lake Christophe", "id": "d3927c17-d049-4ba0-be47-b2b890d157a"},
{"product": "Cheese", "city": "Fort Tess", "sales": 621, "id": "aeaf"},
{"city": "Candiceview", "product": "Sausages", "sales": 430, "id": "9a28bd91-ec13-"},
{"sales": 735, "product": "Chair", "city": "Corwinside", "id": "265d03ab-fcec-4ad9-bc98-99f"},
{"city": "Port Jairofort", "product": "Gloves", "sales": 184, "id": "359212f3-f61f-43"},
{"city": "Chetton", "product": "Pants", "sales": 778, "id": "fa87b"},
{"sales": 284, "product": "Salad", "city": "North Bethesda", "id": "4b02c01d-911e-4b80-"},
{"city": "Lake Aglae", "product": "Chair", "sales": 935, "id": "f3887630-c068-461b-87d"},
{"city": "Lempiton", "product": "Car", "sales": 459, "id": "ca838c11-bbed-"},
{"city": "Durham", "product": "Fish", "sales": 525, "id": "21a43a7d-ed5a-4da0-85c"},
{"product": "Sausages", "city": "New Taryn", "sales": 224, "id": "527d8c82-12fa-4473-a812-74f42773"},
{"product": "Shoes", "city": "Bell Gardens", "sales": 657, "id": "8b0d3fb8-f386-4559-ac53"},
{"product": "Chair", "sales": 923, "city": "Fort Junius", "id": "8600e024-51dc-43e"},
{"city": "North Donatoworth", "product": "Car", "sales": 510, "id": "d056"},
{"city": "West Cielohaven", "product": "Bacon", "sales": 430, "id": "1bceb981-a585-49a5-9bcb"},
{"sales": 899, "product": "Salad", "city": "Gonzaloworth", "id": "84f1cab7-abca-4703-b925-cdf7ef"},
{"city": "South Alfonzo", "product": "Tuna", "sales": 181, "id": "bbc447ac-bbfb-4400-a0ac-0"},
{"city":"Quigleychester","product":"Ball","sales":737},
{"city":"Rosieshire","product":"Soap","sales":963},
{"sales":717,"product":"Bike","city":"Rodrigofurt"},
{"city":"South Karlee","product":"Chicken","sales":183},
{"city":"Baileyfurt","product":"Shoes","sales":728},
{"city":"Haverhill","product":"Table","sales":420},
{"city":"Port Marystead","sales":340,"product":"Chips"},
{"sales":567,"product":"Chips","city":"Crawfordshire"},
{"city":"Port Altashire","product":"Mouse","sales":399},
{"sales":124,"product":"Ball","city":"Jaskolskichester"},
{"city":"Fort Amy","product":"Pizza","sales":108},
{"city":"Millerfield","product":"Bike","sales":129},
{"product":"Gloves","city":"Amyafurt","sales":556},
{"product":"Keyboard","sales":805,"city":"Ortizfort"},
{"product":"Tuna","sales":654,"city":"Alameda"},
{"city":"Kassulkebury","product":"Gloves","sales":850},
{"city":"Hampton","product":"Bacon","sales":519}
]